{
  "root_dir": "..",
  "mailbox": {
    "imap_host": "imap.126.com",
    "imap_port": 993,
    "smtp_host": "smtp.126.com",
    "smtp_port": 465,
    "username": "yourname@126.com",
    "password": "请填写126邮箱授权码",
    "folder": "INBOX"
  },
  "runtime": {
    "state_dir": ".automation"
  },
  "templates": {
    "review_form": "审稿评分表.docx",
    "law_reply": "3. 回复作者/中国政法大学研究生学报作者邮件回复模板（法学）.docx",
    "non_law_reply": "3. 回复作者/中国政法大学研究生学报作者邮件回复模板（法学以外专业）.docx",
    "copyright_agreement": "3. 回复作者/附件一、《研究生学报》著作权使用协议模板.docx"
  },
  "workbook": "2025.04私法组审稿（2025—2026学年）.xlsx",
  "non_law_subjects": [
    "马克思主义理论",
    "政治学",
    "经济学",
    "管理学",
    "社会学",
    "心理学",
    "新闻传播学",
    "人文史哲"
  ],
  "subject_aliases": {
    "民法": ["民法学"],
    "商法": ["公司法", "证券法"],
    "法与经济学": ["法经济学", "法经"],
    "知识产权法": ["知产", "知产法", "知识产权"],
    "经济法": ["财税法", "金融法"],
    "数据法": ["数字法", "数据治理", "算法", "人工智能"],
    "民事诉讼法": ["民诉", "民诉法", "诉讼法"],
    "国际法": ["国际公法", "国际私法"],
    "刑法": ["刑事法", "刑法学"],
    "刑事诉讼法": ["刑诉", "刑诉法"],
    "法理学": ["法理"],
    "宪法与行政法": ["宪法", "行政法"],
    "法律史": ["法史"],
    "马克思主义理论": ["马克思主义"],
    "政治学": ["政治"],
    "经济学": ["经济"],
    "管理学": ["管理"],
    "社会学": ["社会"],
    "心理学": ["心理"],
    "新闻传播学": ["新闻", "传播"],
    "人文史哲": ["哲学", "历史", "人文"]
  },
  "editors_by_subject": {
    "民法": ["王蕙巧", "姚美呈", "史海芳", "李文静"],
    "商法": ["陈海鑫", "陈萱", "张芮铭"],
    "法与经济学": ["陈凌"],
    "知识产权法": ["邢贺通", "王舒骧", "李研"],
    "经济法": ["易征", "王驰传", "杨钧涵"],
    "数据法": ["吴秋雨", "秦思乐", "韩佩芝"],
    "民事诉讼法": ["费美望", "周远航", "杨铮"]
  },
  "preferred_extensions": [".docx", ".doc", ".pdf"]
}
